pop_tools/__init__.py
pop_tools/calc.py
pop_tools/data_registry.txt
pop_tools/datasets.py
pop_tools/eos.py
pop_tools/fill.py
pop_tools/grid.py
pop_tools/inputdata_registry.txt
pop_tools/pop_grid_definitions.yaml
pop_tools/region_mask_definitions.yaml
pop_tools/region_masks.py
pop_tools/xgcm_util.py
pop_tools/input_templates/gx1v6_vert_grid
pop_tools/input_templates/gx1v7_vert_grid
pop_tools/input_templates/gx3v5_vert_grid
pop_tools/input_templates/gx3v7_vert_grid
pop_tools/input_templates/tx0.1v2_vert_grid
pop_tools/input_templates/tx0.1v3_vert_grid
pop_tools/input_templates/tx1v1_vert_grid
pop_tools-2023.6.0.dist-info/LICENSE
pop_tools-2023.6.0.dist-info/METADATA
pop_tools-2023.6.0.dist-info/WHEEL
pop_tools-2023.6.0.dist-info/top_level.txt
pop_tools-2023.6.0.dist-info/RECORD
