Metadata-Version: 2.1
Name: pop-tools
Version: 2023.6.0
Summary: POP2-CESM tools
Home-page: https://github.com/NCAR/pop-tools
Maintainer: Matthew Long
Maintainer-email: mclong@ucar.edu
License: Apache Software License 2.0
Project-URL: Documentation, https://pop-tools.readthedocs.io
Project-URL: Source, https://github.com/NCAR/pop-tools
Project-URL: Tracker, https://github.com/NCAR/pop-tools/issues
Keywords: ocean modeling cesm
Classifier: Development Status :: 4 - Beta
Classifier: License :: OSI Approved :: Apache Software License
Classifier: Operating System :: OS Independent
Classifier: Intended Audience :: Science/Research
Classifier: Programming Language :: Python
Classifier: Programming Language :: Python :: 3
Classifier: Programming Language :: Python :: 3.6
Classifier: Programming Language :: Python :: 3.7
Classifier: Programming Language :: Python :: 3.8
Classifier: Topic :: Scientific/Engineering
Requires-Python: >=3.7
License-File: LICENSE
Requires-Dist: numba (>=0.52)
Requires-Dist: pyyaml (>=5.3.1)
Requires-Dist: xarray (>=0.16.1)
Requires-Dist: dask (>=2.14)
Requires-Dist: pooch (>=1.3.0)
Requires-Dist: numpy (>=1.17.0)
